Cortex-Persist/cortex/core/vsa_hardware_bridge/vsa_tensor_binder.v
`timescale 1ns / 1ps

/*
 * CORTEX Law Ω0 Enforcement.
 * Hardware Sovereign: Silicon-Overlord-Omega
 * Matrix: VSA Tensor Binder (Register-Level Hardware Architecture)
 */
module vsa_tensor_binder #(
    parameter BUS_WIDTH = 256,
    parameter SHIFT_BITS = $clog2(BUS_WIDTH)
)(
    input  wire                   clk,
    input  wire                   rst_n,
    input  wire [BUS_WIDTH-1:0]   tensor_a,
    input  wire [BUS_WIDTH-1:0]   tensor_b,
    input  wire [1:0]             mode,         // 2'b00: XOR, 2'b01: XNOR, 2'b10: PERM_XOR, 2'b11: ACCUMULATE
    input  wire [SHIFT_BITS-1:0]  shift_amount, // Desplazamiento circular para Permutación Rol-Rellenador Pi^k
    input  wire                   bind_enable,
    input  wire                   acc_reset,    // Reset para el acumulador interno de registros
    output reg  [BUS_WIDTH-1:0]   tensor_out,
    output reg  [BUS_WIDTH:0]     popcount,     // Monitoreo de densidad entrópica (Popcount en registro)
    output reg                    entropy_anomaly, // Alerta si popcount == 0 o popcount == BUS_WIDTH
    output reg                    valid
);

    // Modos de binding
    localparam MODE_XOR        = 2'b00;
    localparam MODE_XNOR       = 2'b01;
    localparam MODE_PERM_XOR   = 2'b10;
    localparam MODE_ACCUMULATE = 2'b11;

    // Registros de entrada de etapa 1
    reg [BUS_WIDTH-1:0] reg_a;
    reg [BUS_WIDTH-1:0] reg_b;
    reg [1:0]           reg_mode;
    reg [SHIFT_BITS-1:0] reg_shift;
    reg                 reg_enable;

    // Acumulador interno en banco de registros
    reg [BUS_WIDTH-1:0] acc_reg;

    // Permutación circular de entrada tensor_a (Pi^k(A))
    wire [BUS_WIDTH-1:0] permuted_a;
    assign permuted_a = (reg_shift == 0) ? reg_a :
                        ((reg_a >> reg_shift) | (reg_a << (BUS_WIDTH - reg_shift)));

    // Matriz combinacional de binding
    reg [BUS_WIDTH-1:0] bound_combinational;

    always @(*) begin
        case (reg_mode)
            MODE_XOR:        bound_combinational = reg_a ^ reg_b;
            MODE_XNOR:       bound_combinational = ~(reg_a ^ reg_b);
            MODE_PERM_XOR:   bound_combinational = permuted_a ^ reg_b;
            MODE_ACCUMULATE: bound_combinational = acc_reg ^ (reg_a ^ reg_b);
            default:         bound_combinational = reg_a ^ reg_b;
        endcase
    end

    // Función popcount combinacional para monitoreo de exergía/entropía
    integer i;
    reg [BUS_WIDTH:0] count_temp;
    always @(*) begin
        count_temp = 0;
        for (i = 0; i < BUS_WIDTH; i = i + 1) begin
            if (bound_combinational[i]) begin
                count_temp = count_temp + 1'b1;
            end
        end
    end

    // Etapa de registro de salida y acumulación
    always @(posedge clk or negedge rst_n) begin
        if (!rst_n) begin
            reg_a           <= {BUS_WIDTH{1'b0}};
            reg_b           <= {BUS_WIDTH{1'b0}};
            reg_mode        <= MODE_XOR;
            reg_shift       <= {SHIFT_BITS{1'b0}};
            reg_enable      <= 1'b0;
            tensor_out      <= {BUS_WIDTH{1'b0}};
            acc_reg         <= {BUS_WIDTH{1'b0}};
            popcount        <= {(BUS_WIDTH+1){1'b0}};
            entropy_anomaly <= 1'b0;
            valid           <= 1'b0;
        end else begin
            // Etapa 1: Latch de entradas
            reg_a      <= tensor_a;
            reg_b      <= tensor_b;
            reg_mode   <= mode;
            reg_shift  <= shift_amount;
            reg_enable <= bind_enable;

            if (acc_reset) begin
                acc_reg <= {BUS_WIDTH{1'b0}};
            end

            // Etapa 2: Latch de cómputo y acumulador
            if (reg_enable) begin
                tensor_out      <= bound_combinational;
                acc_reg         <= bound_combinational;
                popcount        <= count_temp;
                entropy_anomaly <= (count_temp == 0) || (count_temp == BUS_WIDTH);
                valid           <= 1'b1;
            end else begin
                valid           <= 1'b0;
            end
        end
    end

    // =========================================================================
    // C5-REAL FORMAL VERIFICATION (Zero-Latency & Cycle Invariant Guarantee)
    // =========================================================================
    `ifdef FORMAL
    always @(posedge clk) begin
        if (rst_n) begin
            if ($past(reg_enable)) begin
                assert(valid == 1'b1);
                assert(popcount <= BUS_WIDTH);
            end
        end
    end
    `endif

endmodule

Cortex-Persist/cortex/core/vsa_hardware_bridge/tb_vsa_tensor_binder.v
`timescale 1ns / 1ps

/*
 * CORTEX-Persist: Testbench for VSA Tensor Binder (Register-Level FPGA Architecture)
 * Validates O(1) Register Spatter Code Binding, Permutations, Accumulation and Popcount Monitoring.
 */
module tb_vsa_tensor_binder;

    parameter BUS_WIDTH = 256;
    parameter SHIFT_BITS = 8;

    reg clk;
    reg rst_n;
    reg [BUS_WIDTH-1:0]  tensor_a;
    reg [BUS_WIDTH-1:0]  tensor_b;
    reg [1:0]            mode;
    reg [SHIFT_BITS-1:0] shift_amount;
    reg                  bind_enable;
    reg                  acc_reset;

    wire [BUS_WIDTH-1:0] tensor_out;
    wire [BUS_WIDTH:0]   popcount;
    wire                 entropy_anomaly;
    wire                 valid;

    vsa_tensor_binder #(
        .BUS_WIDTH(BUS_WIDTH),
        .SHIFT_BITS(SHIFT_BITS)
    ) uut (
        .clk(clk),
        .rst_n(rst_n),
        .tensor_a(tensor_a),
        .tensor_b(tensor_b),
        .mode(mode),
        .shift_amount(shift_amount),
        .bind_enable(bind_enable),
        .acc_reset(acc_reset),
        .tensor_out(tensor_out),
        .popcount(popcount),
        .entropy_anomaly(entropy_anomaly),
        .valid(valid)
    );

    // Clock generation (100MHz)
    initial begin
        clk = 0;
        forever #5 clk = ~clk;
    end

    // Test sequence
    initial begin
        $display("CORTEX-Persist C5-REAL: Iniciando validación VSA Tensor Binder a nivel de registro FPGA");
        $dumpfile("tb_vsa_tensor_binder.vcd");
        $dumpvars(0, tb_vsa_tensor_binder);
        
        // Initialize Inputs
        rst_n = 0;
        tensor_a = {BUS_WIDTH{1'b0}};
        tensor_b = {BUS_WIDTH{1'b0}};
        mode = 2'b00;
        shift_amount = 0;
        bind_enable = 0;
        acc_reset = 0;

        // Reset system
        #20;
        rst_n = 1;
        #10;

        // Test Case 1: Standard XOR binding (Register Pipeline)
        tensor_a = {{(BUS_WIDTH-8){1'b0}}, 8'hAA};
        tensor_b = {{(BUS_WIDTH-8){1'b0}}, 8'h55};
        mode = 2'b00; // MODE_XOR
        bind_enable = 1;
        #20; // 2 ciclos para cruzar el pipeline de registro
        
        if (valid && tensor_out == {{(BUS_WIDTH-8){1'b0}}, 8'hFF}) begin
            $display("[OK] Exergía Conservada: Binding XOR (AA ^ 55 = FF) en Registro.");
        end else begin
            $display("[ERROR] Fallo en Binding XOR. valid=%b, out=%h", valid, tensor_out);
        end
        bind_enable = 0;
        #20;
        
        // Test Case 2: Permute-Bind (Pi^k(A) ^ B)
        tensor_a = {{(BUS_WIDTH-8){1'b0}}, 8'h01}; // 00...00000001
        tensor_b = {BUS_WIDTH{1'b0}};
        mode = 2'b10; // MODE_PERM_XOR
        shift_amount = 4;
        bind_enable = 1;
        #20;

        if (valid && tensor_out[BUS_WIDTH-4]) begin
            $display("[OK] Permutación Rol-Rellenador Pi^4 validada en registro.");
        end else begin
            $display("[ERROR] Fallo en Permute-Bind. out=%h", tensor_out);
        end
        bind_enable = 0;
        #20;

        // Test Case 3: Accumulator & Entropy Popcount Check
        acc_reset = 1;
        #10;
        acc_reset = 0;
        mode = 2'b11; // MODE_ACCUMULATE
        tensor_a = {{(BUS_WIDTH-8){1'b0}}, 8'h0F};
        tensor_b = {{(BUS_WIDTH-8){1'b0}}, 8'hF0};
        bind_enable = 1;
        #20;

        if (valid && popcount == 8) begin
            $display("[OK] Acumulador e Inspección Entrópica (Popcount = 8) validada.");
        end else begin
            $display("[ERROR] Fallo en Popcount/Acumulador. popcount=%d", popcount);
        end

        #40;
        $display("CORTEX-Persist C5-REAL: Validación FPGA en registro finalizada exitosamente.");
        $finish;
    end

endmodule

Cortex-Persist/tb_vsa_tensor_binder.vcd
$date
	Sun Aug  9 21:50:19 2026
$end
$version
	Icarus Verilog
$end
$timescale
	1ps
$end
$scope module tb_vsa_tensor_binder $end
$var wire 1 ! valid $end
$var wire 256 " tensor_out [255:0] $end
$var wire 257 # popcount [256:0] $end
$var wire 1 $ entropy_anomaly $end
$var parameter 32 % BUS_WIDTH $end
$var parameter 32 & SHIFT_BITS $end
$var reg 1 ' acc_reset $end
$var reg 1 ( bind_enable $end
$var reg 1 ) clk $end
$var reg 2 * mode [1:0] $end
$var reg 1 + rst_n $end
$var reg 8 , shift_amount [7:0] $end
$var reg 256 - tensor_a [255:0] $end
$var reg 256 . tensor_b [255:0] $end
$scope module uut $end
$var wire 1 ' acc_reset $end
$var wire 1 ( bind_enable $end
$var wire 1 ) clk $end
$var wire 2 / mode [1:0] $end
$var wire 1 + rst_n $end
$var wire 8 0 shift_amount [7:0] $end
$var wire 256 1 tensor_a [255:0] $end
$var wire 256 2 tensor_b [255:0] $end
$var wire 256 3 permuted_a [255:0] $end
$var parameter 32 4 BUS_WIDTH $end
$var parameter 2 5 MODE_ACCUMULATE $end
$var parameter 2 6 MODE_PERM_XOR $end
$var parameter 2 7 MODE_XNOR $end
$var parameter 2 8 MODE_XOR $end
$var parameter 32 9 SHIFT_BITS $end
$var reg 256 : acc_reg [255:0] $end
$var reg 256 ; bound_combinational [255:0] $end
$var reg 257 < count_temp [256:0] $end
$var reg 1 $ entropy_anomaly $end
$var reg 257 = popcount [256:0] $end
$var reg 256 > reg_a [255:0] $end
$var reg 256 ? reg_b [255:0] $end
$var reg 1 @ reg_enable $end
$var reg 2 A reg_mode [1:0] $end
$var reg 8 B reg_shift [7:0] $end
$var reg 256 C tensor_out [255:0] $end
$var reg 1 ! valid $end
$var integer 32 D i [31:0] $end
$upscope $end
$upscope $end
$enddefinitions $end
$comment Show the parameter values. $end
$dumpall
b1000 9
b0 8
b1 7
b10 6
b11 5
b100000000 4
b1000 &
b100000000 %
$end
#0
$dumpvars
b100000000 D
b0 C
b0 B
b0 A
0@
b0 ?
b0 >
b0 =
b0 <
b0 ;
b0 :
b0 3
b0 2
b0 1
b0 0
b0 /
b0 .
b0 -
b0 ,
0+
b0 *
0)
0(
0'
0$
b0 #
b0 "
0!
$end
#5000
1)
#10000
0)
#15000
1)
#20000
0)
1+
#25000
1)
#30000
0)
1(
b1010101 .
b1010101 2
b10101010 -
b10101010 1
#35000
b1000 <
b100000000 D
b11111111 ;
b10101010 3
1@
b1010101 ?
b10101010 >
1)
#40000
0)
#45000
1!
b1000 #
b1000 =
b11111111 :
b11111111 "
b11111111 C
1)
#50000
0)
0(
#55000
0@
1)
#60000
0)
#65000
0!
1)
#70000
0)
1(
b100 ,
b100 0
b10 *
b10 /
b0 .
b0 2
b1 -
b1 1
#75000
b100000000 D
b1 <
b1000000000000000000000000000000000000000000000000000000000000000000000000000000000000000000000000000000000000000000000000000000000000000000000000000000000000000000000000000000000000000000000000000000000000000000000000000000000000000000000000000000000000 ;
b1000000000000000000000000000000000000000000000000000000000000000000000000000000000000000000000000000000000000000000000000000000000000000000000000000000000000000000000000000000000000000000000000000000000000000000000000000000000000000000000000000000000000 3
1@
b100 B
b10 A
b0 ?
b1 >
1)
#80000
0)
#85000
1!
b1 #
b1 =
b1000000000000000000000000000000000000000000000000000000000000000000000000000000000000000000000000000000000000000000000000000000000000000000000000000000000000000000000000000000000000000000000000000000000000000000000000000000000000000000000000000000000000 :
b1000000000000000000000000000000000000000000000000000000000000000000000000000000000000000000000000000000000000000000000000000000000000000000000000000000000000000000000000000000000000000000000000000000000000000000000000000000000000000000000000000000000000 "
b1000000000000000000000000000000000000000000000000000000000000000000000000000000000000000000000000000000000000000000000000000000000000000000000000000000000000000000000000000000000000000000000000000000000000000000000000000000000000000000000000000000000000 C
1)
#90000
0)
0(
#95000
0@
1)
#100000
0)
#105000
0!
1)
#110000
0)
1'
#115000
b0 :
1)
#120000
0)
1(
b11110000 .
b11110000 2
b1111 -
b1111 1
b11 *
b11 /
0'
#125000
b100000000 D
b1000 <
b1111000000000000000000000000000000000000000000000000000000000000000000000000000000000000000000000000000000000000000000000000000000000000000000000000000000000000000000000000000000000000000000000000000000000000000000000000000000000000000000000000000000000000 3
b11111111 ;
1@
b11 A
b11110000 ?
b1111 >
1)
#130000
0)
#135000
b100000000 D
b0 <
b0 ;
1!
b1000 #
b1000 =
b11111111 :
b11111111 "
b11111111 C
1)
#140000
0)
#145000
b1000 <
b100000000 D
b11111111 ;
1$
b0 #
b0 =
b0 :
b0 "
b0 C
1)
#150000
0)
#155000
b100000000 D
b0 <
b0 ;
0$
b1000 #
b1000 =
b11111111 :
b11111111 "
b11111111 C
1)
#160000
0)
#165000
b1000 <
b100000000 D
b11111111 ;
1$
b0 #
b0 =
b0 :
b0 "
b0 C
1)
#170000
0)
#175000
b100000000 D
b0 <
b0 ;
0$
b1000 #
b1000 =
b11111111 :
b11111111 "
b11111111 C
1)
